fil_finder/__init__.py
fil_finder/_astropy_init.py
fil_finder/base_conversions.py
fil_finder/conftest.py
fil_finder/cores.py
fil_finder/filament.py
fil_finder/filfind_class.py
fil_finder/filfinder2D.py
fil_finder/io_funcs.py
fil_finder/length.py
fil_finder/pixel_ident.py
fil_finder/rollinghough.py
fil_finder/utilities.py
fil_finder/version.py
fil_finder/width.py
fil_finder/tests/__init__.py
fil_finder/tests/_testing_data.py
fil_finder/tests/setup_package.py
fil_finder/tests/test_baseclasses.py
fil_finder/tests/test_filament2D.py
fil_finder/tests/test_init.py
fil_finder/tests/test_input_types.py
fil_finder/tests/test_lengths.py
fil_finder/tests/test_masking.py
fil_finder/tests/test_profiles.py
fil_finder/tests/test_rht.py
fil_finder/tests/test_utilities.py
fil_finder/tests/test_whole.py
fil_finder/tests/test_whole_simplefilament.py
fil_finder/tests/test_widths.py
fil_finder/tests/testing_utils.py
fil_finder/tests/data/_generate_testing_data.py
fil_finder/tests/data/filaments_updatedhdr.fits
fil_finder/tests/data/generate_noise_model.py
fil_finder/tests/data/test1_filament_model.fits
fil_finder/tests/data/test1_mask.fits
fil_finder/tests/data/test1_skeletons.fits
fil_finder/tests/data/test1_table.hdf5
fil_finder/tests/data/test1_table_branch.hdf5
fil_finder/tests/data/test2_filament_model.fits
fil_finder/tests/data/test2_mask.fits
fil_finder/tests/data/test2_skeletons.fits
fil_finder/tests/data/test2_table.hdf5
fil_finder/tests/data/test2_table_branch.hdf5
fil_finder/width_profiles/__init__.py
fil_finder/width_profiles/profile.py
fil_finder/width_profiles/profile_line_width.py
fil_finder-1.7.2.dist-info/LICENSE.rst
fil_finder-1.7.2.dist-info/METADATA
fil_finder-1.7.2.dist-info/WHEEL
fil_finder-1.7.2.dist-info/top_level.txt
fil_finder-1.7.2.dist-info/RECORD
