Metadata-Version: 2.1
Name: fil-finder
Version: 1.7.2
Summary: Detection of filamentary structure in molecular clouds
Home-page: http://fil-finder.readthedocs.io
Author: Eric Koch and Erik Rosolowsky
Author-email: koch.eric.w@gmail.com
License: MIT
Platform: UNKNOWN
Requires-Python: >=3.7
Provides-Extra: test
Provides-Extra: docs
License-File: LICENSE.rst
